Workbook

Sheet Historical Data
B3: Eternal Ltd. Financial Model
B4: (Formerly Zomato Limited) | C4: Circuit Switch: | D4: ON
C5: Operating scenario: | D5: Base Case
C6: Target Price: | D6: 71.85
B9: All figures in ₹ Cr unless otherwise stated
C10: Historical Income Statement
B11: Income Statement(₹ Cr) | C11: FY23A | D11: FY24A | E11: FY25A
B13: [Income Statement]
B14: Income:
B15: Revenue from Operations | C15: 7079 | D15: 12114 | E15: 20243
B16: Other Income | C16: 682 | D16: 847 | E16: 1077
B17: Toatal Income | C17: =SUM(C15:C16) -> 7761 | D17: =SUM(D15:D16) -> 12961 | E17: =SUM(E15:E16) -> 21320
B19: Operating Expenses:
B20: Purchase of Stock-in-Trade | C20: 1438 | D20: 2887 | E20: 5653
B21: Changes in Inventories | C21: -43 | D21: -5 | E21: -88
B22: Employee Benefits Expense | C22: 1465 | D22: 1659 | E22: 2558
B23: Finance Costs | C23: 49 | D23: 72 | E23: 154
B24: Depreciation and Amortization | C24: 437 | D24: 526 | E24: 863
B25: Other Expenses | C25: 5429 | D25: 7531 | E25: 11483
B26: Total Expenses | C26: =SUM(C20:C25) -> 8775 | D26: =SUM(D20:D25) -> 12670 | E26: =SUM(E20:E25) -> 20623
B27: PBT | C27: =C17-C26 -> -1014 | D27: =D17-D26 -> 291 | E27: =E17-E26 -> 697
B28: Tax Expenses | C28: 44 | D28: -60 | E28: 170
B29: Net Income (PAT) | C29: =C27-C28 -> -1058 | D29: =D27-D28 -> 351 | E29: =E27-E28 -> 527
C32: Historical Balance Sheet
B33: Balance Sheet(₹ Cr) | C33: FY23A | D33: FY24A | E33: FY25A
B35: [Balance Sheet]
B36: ASSETS
B37: NON-CURRENT ASSETS
B38: Property, Plant and Equipment | C38: 209 | D38: 287 | E38: 965
B39: Capital Work-in-Progress | C39: 7 | D39: 18 | E39: 51
B40: Right-of-use Asset | C40: 427 | D40: 690 | E40: 1918
B41: Goodwill | C41: 4717 | D41: 4717 | E41: 5737
B42: Other Intangible Assets | C42: 991 | D42: 754 | E42: 912
B43: Investments (Non-current) | C43: 2280 | D43: 10365 | E43: 10920
B44: Other Financial Assets (Non-current) | C44: 1894 | D44: 747 | E44: 2744
B45: Tax Assets (Net) | C45: 116 | D45: 221 | E45: 129
B46: Other Non-current Assets | C46: 127 | D46: 99 | E46: 546
B47: TOTAL NON-CURRENT ASSETS | C47: =SUM(C38:C46) -> 10768 | D47: =SUM(D38:D46) -> 17898 | E47: =SUM(E38:E46) -> 23922
B49: CURRENT ASSETS
B50: Inventories | C50: 83 | D50: 88 | E50: 176
B51: Investments (Current) | C51: 4485 | D51: 1280 | E51: 2272
B52: Trade Receivables | C52: 457 | D52: 794 | E52: 1946
B53: Cash and Cash Equivalents | C53: 218 | D53: 309 | E53: 666
B54: Bank Balances Other than Cash and Cash Equivalents | C54: 799 | D54: 422 | E54: 2948
B55: Loans | C55: 0 | D55: 0 | E55: 0
B56: Other Financial Assets (Current) | C56: 4418 | D56: 2324 | E56: 2769
B57: Other Current Assets | C57: 371 | D57: 241 | E57: 924
B58: TOTAL CURRENT ASSETS | C58: =SUM(C50:C57) -> 10831 | D58: =SUM(D50:D57) -> 5458 | E58: =SUM(E50:E57) -> 11701
B60: TOTAL ASSETS | C60: =SUM(C47+C58) -> 21599 | D60: =SUM(D47+D58) -> 23356 | E60: =SUM(E47+E58) -> 35623
B62: EQUITY
B63: Equity Share Capital | C63: 836 | D63: 868 | E63: 907
B64: Other Equity | C64: 18624 | D64: 19545 | E64: 29410
B65: Non-controlling Interests | C65: -7 | D65: -7 | E65: -7
B66: TOTAL EQUITY | C66: =SUM(C63:C65) -> 19453 | D66: =SUM(D63:D65) -> 20406 | E66: =SUM(E63:E65) -> 30310
B68: NON-CURRENT LIABILITIES
B69: Borrowings (Non-current) | C69: 6 | D69: - | E69: -
B70: Lease Liabilities (Non-current) | C70: 351 | D70: 588 | E70: 1654
B71: Other Financial Liabilities (Non-current) | C71: 95 | D71: 3 | E71: 1
B72: Provisions (Non-current) | C72: 4 | D72: 88 | E72: 120
B73: Deferred Tax Liabilities | C73: 249 | D73: 188 | E73: 212
B74: TOTAL NON-CURRENT LIABILITIES | C74: =SUM(C69:C73) -> 705 | D74: =SUM(D69:D73) -> 867 | E74: =SUM(E69:E73) -> 1987
B76: CURRENT LIABILITIES
B77: Borrowings (Current) | C77: 35 | D77: - | E77: -
B78: Lease Liabilities (Current) | C78: 115 | D78: 161 | E78: 391
B79: Trade Payables | C79: 679 | D79: 886 | E79: 1536
B80: Other Financial Liabilities (Current) | C80: 310 | D80: 644 | E80: 913
B81: Other Current Liabilities | C81: 276 | D81: 363 | E81: 452
B82: Provisions (Current) | C82: 26 | D82: 29 | E82: 34
B83: TOTAL CURRENT LIABILITIES | C83: =SUM(C77:C82) -> 1441 | D83: =SUM(D77:D82) -> 2083 | E83: =SUM(E77:E82) -> 3326
B84: TOTAL LIABILITIES | C84: =SUM(C74+C83) -> 2146 | D84: =SUM(D74+D83) -> 2950 | E84: =SUM(E74+E83) -> 5313
B86: TOTAL EQUITY AND LIABILITIES | C86: =SUM(C66+C84) -> 21599 | D86: =SUM(D66+D84) -> 23356 | E86: =SUM(E66+E84) -> 35623
C89: Historical Cash Flow Statement
B90: Cash Flow Statement(₹ Cr) | C90: FY23A | D90: FY24A | E90: FY25A
B92: [Cash Flow Statement]
B93: CASH FLOWS FROM OPERATING ACTIVITIES
B94: Profit Before Tax | C94: =C29 -> -1058 | D94: =D29 -> 351 | E94: =E29 -> 527
B95: Depreciation & Amortisation | C95: 437 | D95: 526 | E95: 863
B96: Share Based Payments | C96: 506 | D96: 515 | E96: 798
B97: Finance Costs | C97: 46 | D97: 69 | E97: 151
B98: Expected Credit Loss / Provisions | C98: 31 | D98: 69 | E98: 71
B99: Other Non-Cash Adjustments | C99: -14 | D99: -50 | E99: -103
B100: Interest Income | C100: -529 | D100: -648 | E100: -815
B101: Investment & Asset Gains | C101: -100 | D101: -139 | E101: -143
B102: Share of Profit/Loss from Associates (if material) | C102: 1 | D102: 0 | E102: 0
B103: Operating Profit before Working Capital Changes | C103: =SUM(C94:C102) -> -680 | D103: =SUM(D94:D102) -> 693 | E103: =SUM(E94:E102) -> 1349
B104: Trade receivables | C104: -203 | D104: -348 | E104: -1117
B105: Inventory | C105: -43 | D105: -5 | E105: -88
B106: Trade payables | C106: -71 | D106: 211 | E106: 629
B107: Other operating assets | C107: -202 | D107: -159 | E107: -812
B108: Other operating liabilities | C108: 343 | D108: 419 | E108: 295
B109: Operating Profit after Working Capital Changes | C109: =SUM(C104:C108) -> -176 | D109: =SUM(D104:D108) -> 118 | E109: =SUM(E104:E108) -> -1093
B110: Cash Generated from Operations | C110: =C103+C109 -> -856 | D110: =D103+D109 -> 811 | E110: =E103+E109 -> 256
B111: Income taxes refund / (paid) (net) | C111: -31 | D111: -105 | E111: -118
B112: Net cash generated from / (used in) operating activities (A) | C112: =SUM(C110:C111) -> -887 | D112: =SUM(D110:D111) -> 706 | E112: =SUM(E110:E111) -> 138
B114: CASH FLOWS FROM INVESTING ACTIVITIES
B115: CapEx | C115: -103 | D115: -215 | E115: -936
B116: Sale of fixed assets | C116: 2 | D116: 13 | E116: 5
B117: Investment Purchases | C117: -20491 | D117: -37146 | E117: -55671
B118: Investment redemptions | C118: 21370 | D118: 36383 | E118: 49795
B119: Acquisitions | C119: -61 | D119: 0 | E119: -2005
...

Sheet Assumptions
B2: Assumption | C2: FY26E | D2: FY27E | E2: FY28E | F2: FY29E | G2: FY30E
B3: Revenue Growth | C3: 0.3 | D3: 0.25 | E3: 0.2 | F3: 0.15 | G3: 0.12
B4: Other Income Growth | C4: 0.1 | D4: 0.1 | E4: 0.1 | F4: 0.1 | G4: 0.1
B5: COGS % Revenue | C5: 0.28 | D5: 0.28 | E5: 0.28 | F5: 0.28 | G5: 0.28
B6: Employee Cost % Revenue | C6: 0.125 | D6: 0.12 | E6: 0.115 | F6: 0.11 | G6: 0.105
B7: Other Expense % Revenue | C7: 0.55 | D7: 0.53 | E7: 0.51 | F7: 0.49 | G7: 0.48
B8: D&A % Revenue | C8: 0.04 | D8: 0.04 | E8: 0.04 | F8: 0.04 | G8: 0.04
B9: Finance Cost (₹ Cr) | C9: 154 | D9: 154 | E9: 154 | F9: 154 | G9: 154
B10: Tax Rate | C10: 0.25 | D10: 0.25 | E10: 0.25 | F10: 0.25 | G10: 0.25
B11: Receivable Days | C11: 35 | D11: 34 | E11: 33 | F11: 32 | G11: 31
B12: Payable Days | C12: 95 | D12: 92 | E12: 90 | F12: 88 | G12: 85
A13: Advertising & marketing is approximately 25-30% of Other Expenses based on management commentary. Not modeled separately for simplicity." | B13: Capex % Revenue | C13: 0.06 | D13: 0.06 | E13: 0.05 | F13: 0.05 | G13: 0.04
B14: Inventory days | C14: 11 | D14: 11 | E14: 11 | F14: 11 | G14: 11
B15: Share based compensation | C15: 798 | D15: 850 | E15: 900 | F15: 950 | G15: 1000
B16: Other current liabilities % revenue | C16: ='Financial Model'!C57/'Financial Model'!C4 -> 0.022328706 | D16: ='Financial Model'!D57/'Financial Model'!D4 -> 0.022328706 | E16: ='Financial Model'!E57/'Financial Model'!E4 -> 0.022328706 | F16: ='Financial Model'!F57/'Financial Model'!F4 -> 0.022328706 | G16: ='Financial Model'!G57/'Financial Model'!G4 -> 0.022328706
B19: Lease Schedule
B20: (₹ Cr) | C20: FY26 | D20: FY27 | E20: FY28 | F20: FY29 | G20: FY30
B21: Opening ROU | C21: 1918 | D21: 2078 | E21: 2253 | F21: =E24 -> 2403 | G21: =F24 -> 2554.6667
B22: New Leases (40% of CapEx) | C22: 240 | D22: 300 | E22: 250 | F22: 273.33333 | G22: 273.33333
B23: Lease Depreciation (included in D&A) | C23: -80 | D23: -125 | E23: -100 | F23: -121.66667 | G23: -121.66667
B24: Closing ROU | C24: =SUM(C21:C23) -> 2078 | D24: =SUM(D21:D23) -> 2253 | E24: =SUM(E21:E23) -> 2403 | F24: =SUM(F21:F23) -> 2554.6667 | G24: =SUM(G21:G23) -> 2706.3333

Sheet Financial Model
B2: All figures in ₹ Cr unless otherwise stated
B3: Forecast Income Statement (₹ Cr) | C3: FY25E | D3: FY26E | E3: FY27E | F3: FY28E | G3: FY29E | H3: FY30E
B4: Revenue | C4: ='Historical Data'!E15 -> 20243 | D4: =C4*(1+Assumptions!C3) -> 26315.9 | E4: =D4*(1+Assumptions!D3) -> 32894.875 | F4: =E4*(1+Assumptions!E3) -> 39473.85 | G4: =F4*(1+Assumptions!F3) -> 45394.927 | H4: =G4*(1+Assumptions!G3) -> 50842.319
B5: Other Income | C5: ='Historical Data'!E16 -> 1077 | D5: =C5*(1+Assumptions!C4) -> 1184.7 | E5: =D5*(1+Assumptions!D4) -> 1303.17 | F5: =E5*(1+Assumptions!E4) -> 1433.487 | G5: =F5*(1+Assumptions!F4) -> 1576.8357 | H5: =G5*(1+Assumptions!G4) -> 1734.5193
B6: Total Income | C6: =SUM(C4:C5) -> 21320 | D6: =SUM(D4:D5) -> 27500.6 | E6: =SUM(E4:E5) -> 34198.045 | F6: =SUM(F4:F5) -> 40907.337 | G6: =SUM(G4:G5) -> 46971.763 | H6: =SUM(H4:H5) -> 52576.838
B7: COGS | D7: =D4*Assumptions!C5 -> 7368.452 | E7: =E4*Assumptions!D5 -> 9210.565 | F7: =F4*Assumptions!E5 -> 11052.678 | G7: =G4*Assumptions!F5 -> 12710.58 | H7: =H4*Assumptions!G5 -> 14235.849
B8: Employee Benefits | D8: =D4*Assumptions!C6 -> 3289.4875 | E8: =E4*Assumptions!D6 -> 3947.385 | F8: =F4*Assumptions!E6 -> 4539.4928 | G8: =G4*Assumptions!F6 -> 4993.442 | H8: =H4*Assumptions!G6 -> 5338.4435
B9: Depreciation & Amortization | D9: =D4*Assumptions!C8 -> 1052.636 | E9: =E4*Assumptions!D8 -> 1315.795 | F9: =F4*Assumptions!E8 -> 1578.954 | G9: =G4*Assumptions!F8 -> 1815.7971 | H9: =H4*Assumptions!G8 -> 2033.6928
B10: Finance Costs | D10: =Assumptions!C9 -> 154 | E10: =Assumptions!D9 -> 154 | F10: =Assumptions!E9 -> 154 | G10: =Assumptions!F9 -> 154 | H10: =Assumptions!G9 -> 154
B11: Other Expenses | D11: =D4*Assumptions!C7 -> 14473.745 | E11: =E4*Assumptions!D7 -> 17434.284 | F11: =F4*Assumptions!E7 -> 20131.663 | G11: =G4*Assumptions!F7 -> 22243.514 | H11: =H4*Assumptions!G7 -> 24404.313
B12: Total Expenses | D12: =SUM(D7:D11) -> 26338.321 | E12: =SUM(E7:E11) -> 32062.029 | F12: =SUM(F7:F11) -> 37456.788 | G12: =SUM(G7:G11) -> 41917.333 | H12: =SUM(H7:H11) -> 46166.299
B13: PBT | D13: =D6-D12 -> 1162.2795 | E13: =E6-E12 -> 2136.0162 | F13: =F6-F12 -> 3450.5488 | G13: =G6-G12 -> 5054.4299 | H13: =H6-H12 -> 6410.5396
B14: Tax | D14: =IF(D13>0,D13*Assumptions!C10,0) -> 290.56988 | E14: =IF(E13>0,E13*Assumptions!D10,0) -> 534.00406 | F14: =IF(F13>0,F13*Assumptions!E10,0) -> 862.63719 | G14: =IF(G13>0,G13*Assumptions!F10,0) -> 1263.6075 | H14: =IF(H13>0,H13*Assumptions!G10,0) -> 1602.6349
B15: Net Income (PAT) | D15: =D13-D14 -> 871.70963 | E15: =E13-E14 -> 1602.0122 | F15: =F13-F14 -> 2587.9116 | G15: =G13-G14 -> 3790.8224 | H15: =H13-H14 -> 4807.9047
B18: Forecast Balance Sheet (₹ Cr) | C18: FY25E | D18: FY26E | E18: FY27E | F18: FY28E | G18: FY29E | H18: FY30E
B20: ASSETS:
B21: Trade Receivables | C21: ='Historical Data'!E52 -> 1946 | D21: =D4*Assumptions!C11/365 -> 2523.4425 | E21: =E4*Assumptions!D11/365 -> 3064.1801 | F21: =F4*Assumptions!E11/365 -> 3568.8686 | G21: =G4*Assumptions!F11/365 -> 3979.8293 | H21: =H4*Assumptions!G11/365 -> 4318.1147
B22: Inventory | C22: ='Historical Data'!E50 -> 176 | D22: =D7*Assumptions!C14/365 -> 222.06294 | E22: =E7*Assumptions!D14/365 -> 277.57867 | F22: =F7*Assumptions!E14/365 -> 333.09441 | G22: =G7*Assumptions!F14/365 -> 383.05857 | H22: =H7*Assumptions!G14/365 -> 429.02559
B23: Current Investments | C23: ='Historical Data'!E51 -> 2272 | D23: 2272 | E23: 2272 | F23: 2272 | G23: 2272 | H23: 2272
B24: Bank balance other than cash | C24: ='Historical Data'!E54 -> 2948 | D24: 2948 | E24: 2948 | F24: 2948 | G24: 2948 | H24: 2948
B25: Other Financial Assets | C25: ='Historical Data'!E56 -> 2769 | D25: 2769 | E25: 2769 | F25: 2769 | G25: 2769 | H25: 2769
B26: Other Current Assets | C26: 924 | D26: =D4*(C26/C4) -> 1201.2 | E26: =E4*(D26/D4) -> 1501.5 | F26: =F4*(E26/E4) -> 1801.8 | G26: =G4*(F26/F4) -> 2072.07 | H26: =H4*(G26/G4) -> 2320.7184
B27: Cash & Cash Equivalents | C27: ='Historical Data'!E53 -> 666 | D27: =D93 -> 1346.1025 | E27: =E93 -> 2669.3146 | F27: =F93 -> 5352.6342 | G27: =G93 -> 9258.0066 | H27: =H93 -> 14683.706
B28: Total Current Assets | C28: =SUM(C21:C27) -> 11701 | D28: =SUM(D21:D27) -> 13281.808 | E28: =SUM(E21:E27) -> 15501.573 | F28: =SUM(F21:F27) -> 19045.397 | G28: =SUM(G21:G27) -> 23681.964 | H28: =SUM(H21:H27) -> 29740.565
B29: PPE | C29: ='Historical Data'!E38 -> 965 | D29: =C29-D80-(D69+Assumptions!C23) -> 1571.318 | E29: =D29-E80-(E69+Assumptions!D23) -> 2354.2155 | F29: =E29-F80-(F69+Assumptions!E23) -> 2848.954 | G29: =F29-G80-(G69+Assumptions!F23) -> 3424.5699 | H29: =G29-H80-(H69+Assumptions!G23) -> 3546.2366
B30: CWIP | C30: ='Historical Data'!E39 -> 51 | D30: 51 | E30: 51 | F30: 51 | G30: 51 | H30: 51
B31: ROU Asset | C31: ='Historical Data'!E40 -> 1918 | D31: =Assumptions!C24 -> 2078 | E31: =Assumptions!D24 -> 2253 | F31: =Assumptions!E24 -> 2403 | G31: =Assumptions!F24 -> 2554.6667 | H31: =Assumptions!G24 -> 2706.3333
B32: Goodwill | C32: ='Historical Data'!E41 -> 5737 | D32: 5737 | E32: 5737 | F32: 5737 | G32: 5737 | H32: 5737
B33: Intangibles | C33: ='Historical Data'!E42 -> 912 | D33: 912 | E33: 912 | F33: 912 | G33: 912 | H33: 912
B34: Investments | C34: ='Historical Data'!E43 -> 10920 | D34: 10920 | E34: 10920 | F34: 10920 | G34: 10920 | H34: 10920
B35: Other Financial Assets | C35: ='Historical Data'!E44 -> 2744 | D35: 2744 | E35: 2744 | F35: 2744 | G35: 2744 | H35: 2744
B36: Tax Assets | C36: ='Historical Data'!E45 -> 129 | D36: 129 | E36: 129 | F36: 129 | G36: 129 | H36: 129
B37: Other Non-Current Assets | C37: ='Historical Data'!E46 -> 546 | D37: 546 | E37: 546 | F37: 546 | G37: 546 | H37: 546
B38: Total Non-Current Assets | C38: =SUM(C29:C37) -> 23922 | D38: =SUM(D29:D37) -> 24688.318 | E38: =SUM(E29:E37) -> 25646.215 | F38: =SUM(F29:F37) -> 26290.954 | G38: =SUM(G29:G37) -> 27018.237 | H38: =SUM(H29:H37) -> 27291.57
B40: TOTAL ASSETS | C40: =C28+C38 -> 35623 | D40: =D28+D38 -> 37970.126 | E40: =E28+E38 -> 41147.789 | F40: =F28+F38 -> 45336.351 | G40: =G28+G38 -> 50700.201 | H40: =H28+H38 -> 57032.135
B43: LIABILITIES & EQUITY:
B44: Equity Share Capital | C44: ='Historical Data'!E63 -> 907 | D44: 907 | E44: 907 | F44: 907 | G44: 907 | H44: 907
B45: Other Equity | C45: ='Historical Data'!E64 -> 29410 | D45: =C45+D15+Assumptions!C15 -> 31079.71 | E45: =D45+E15+Assumptions!D15 -> 33531.722 | F45: =E45+F15+Assumptions!E15 -> 37019.633 | G45: =F45+G15+Assumptions!F15 -> 41760.456 | H45: =G45+H15+Assumptions!G15 -> 47568.36
B46: TOTAL EQUITY | C46: =SUM(C44:C45) -> 30317 | D46: =SUM(D44:D45) -> 31986.71 | E46: =SUM(E44:E45) -> 34438.722 | F46: =SUM(F44:F45) -> 37926.633 | G46: =SUM(G44:G45) -> 42667.456 | H46: =SUM(H44:H45) -> 48475.36
B47: NCI | C47: ='Historical Data'!E65 -> -7 | D47: -7 | E47: -7 | F47: -7 | G47: -7 | H47: -7
B49: Lease Liabilities (Non-current) | C49: ='Historical Data'!E70 -> 1654 | D49: =(C49+C55+Assumptions!C22+Assumptions!C23)*0.8 -> 1764 | E49: =(D49+D55+Assumptions!D22+Assumptions!D23)*0.8 -> 1904 | F49: =(E49+E55+Assumptions!E22+Assumptions!E23)*0.8 -> 2024 | G49: =(F49+F55+Assumptions!F22+Assumptions!F23)*0.8 -> 2145.3333 | H49: =(G49+G55+Assumptions!G22+Assumptions!G23)*0.8 -> 2266.6667
B50: Provisions(NC) | C50: ='Historical Data'!E72 -> 120 | D50: 120 | E50: 120 | F50: 120 | G50: 120 | H50: 120
B51: Deferred Tax Liabilitits | C51: ='Historical Data'!E73 -> 212 | D51: 212 | E51: 212 | F51: 212 | G51: 212 | H51: 212
B52: Other Financial Liabilities | C52: ='Historical Data'!E71 -> 1 | D52: 1 | E52: 1 | F52: 1 | G52: 1 | H52: 1
B53: Total Non-Current Liabilities | C53: =SUM(C49:C52) -> 1987 | D53: =SUM(D49:D52) -> 2097 | E53: =SUM(E49:E52) -> 2237 | F53: =SUM(F49:F52) -> 2357 | G53: =SUM(G49:G52) -> 2478.3333 | H53: =SUM(H49:H52) -> 2599.6667
B55: Lease Liabilities (Current) | C55: ='Historical Data'!E78 -> 391 | D55: =(C49+C55+Assumptions!C22+Assumptions!C23)*0.2 -> 441 | E55: =(D49+D55+Assumptions!D22+Assumptions!D23)*0.2 -> 476 | F55: =(E49+E55+Assumptions!E22+Assumptions!E23)*0.2 -> 506 | G55: =(F49+F55+Assumptions!F22+Assumptions!F23)*0.2 -> 536.33333 | H55: =(G49+G55+Assumptions!G22+Assumptions!G23)*0.2 -> 566.66667
B56: Other Financial Liabilities | C56: ='Historical Data'!E80 -> 913 | D56: 913 | E56: 913 | F56: 913 | G56: 913 | H56: 913
B57: Other Current Liabilities | C57: ='Historical Data'!E81 -> 452 | D57: =D4*Assumptions!C16 -> 587.6 | E57: =E4*Assumptions!D16 -> 734.5 | F57: =F4*Assumptions!E16 -> 881.4 | G57: =G4*Assumptions!F16 -> 1013.61 | H57: =H4*Assumptions!G16 -> 1135.2432
B58: Trade Payables | C58: ='Historical Data'!E79 -> 1536 | D58: =D7*Assumptions!C12/365 -> 1917.8163 | E58: =E7*Assumptions!D12/365 -> 2321.5671 | F58: =F7*Assumptions!E12/365 -> 2725.3179 | G58: =G7*Assumptions!F12/365 -> 3064.4685 | H58: =H7*Assumptions!G12/365 -> 3315.1978
B59: Provisions(Current) | C59: ='Historical Data'!E82 -> 34 | D59: 34 | E59: 34 | F59: 34 | G59: 34 | H59: 34
B60: Total Current Liabilities | C60: =SUM(C55:C59) -> 3326 | D60: =SUM(D55:D59) -> 3893.4163 | E60: =SUM(E55:E59) -> 4479.0671 | F60: =SUM(F55:F59) -> 5059.7179 | G60: =SUM(G55:G59) -> 5561.4119 | H60: =SUM(H55:H59) -> 5964.1076
B62: TOTAL LIABILITIES + EQUITY | C62: =C46+C47+C53+C60 -> 35623 | D62: =D46+D47+D53+D60 -> 37970.126 | E62: =E46+E47+E53+E60 -> 41147.789 | F62: =F46+F47+F53+F60 -> 45336.351 | G62: =G46+G47+G53+G60 -> 50700.201 | H62: =H46+H47+H53+H60 -> 57032.135
B65: Forecast Cash Flow Statement (₹ Cr) | C65: FY25E | D65: FY26 | E65: FY27 | F65: FY28 | G65: FY29 | H65: FY30
B66: Operating Activities
B67: Net Income (PAT) | C67: =C15 -> 0 | D67: =D15 -> 871.70963 | E67: =E15 -> 1602.0122 | F67: =F15 -> 2587.9116 | G67: =G15 -> 3790.8224 | H67: =H15 -> 4807.9047
B68: Interest receieved | D68: =-D5 -> -1184.7 | E68: =-E5 -> -1303.17 | F68: =-F5 -> -1433.487 | G68: =-G5 -> -1576.8357 | H68: =-H5 -> -1734.5193
B69: Depreciation & Amortization | D69: =D9 -> 1052.636 | E69: =E9 -> 1315.795 | F69: =F9 -> 1578.954 | G69: =G9 -> 1815.7971 | H69: =H9 -> 2033.6928
B70: Increase in Receivables | D70: =-(D21-C21) -> -577.44247 | E70: =-(E21-D21) -> -540.73767 | F70: =-(F21-E21) -> -504.68849 | G70: =-(G21-F21) -> -410.96063 | H70: =-(H21-G21) -> -338.28549
B71: Increase in Inventory | D71: =-(D22-C22) -> -46.062937 | E71: =-(E22-D22) -> -55.515734 | F71: =-(F22-E22) -> -55.515734 | G71: =-(G22-F22) -> -49.964161 | H71: =-(H22-G22) -> -45.967028
B72: Increase in Payables | D72: =D58-C58 -> 381.81627 | E72: =E58-D58 -> 403.75079 | F72: =F58-E58 -> 403.75079 | G72: =G58-F58 -> 339.15067 | H72: =H58-G58 -> 250.72924
B73: Increase in other current assets | D73: =-(D26-C26) -> -277.2 | E73: =-(E26-D26) -> -300.3 | F73: =-(F26-E26) -> -300.3 | G73: =-(G26-F26) -> -270.27 | H73: =-(H26-G26) -> -248.6484
B74: Increase in other current liabilities | D74: =D57-C57 -> 135.6 | E74: =E57-D57 -> 146.9 | F74: =F57-E57 -> 146.9 | G74: =G57-F57 -> 132.21 | H74: =H57-G57 -> 121.6332
B75: Share based payments | D75: =Assumptions!C15 -> 798 | E75: =Assumptions!D15 -> 850 | F75: =Assumptions!E15 -> 900 | G75: =Assumptions!F15 -> 950 | H75: =Assumptions!G15 -> 1000
B76: Finance cost | D76: =D10 -> 154 | E76: =E10 -> 154 | F76: =F10 -> 154 | G76: =G10 -> 154 | H76: =H10 -> 154
B77: Net Cash from Operating Activities | D77: =SUM(D67:D76) -> 1308.3565 | E77: =SUM(E67:E76) -> 2272.7346 | F77: =SUM(F67:F76) -> 3477.5251 | G77: =SUM(G67:G76) -> 4873.9497 | H77: =SUM(H67:H76) -> 6000.5397
B79: Investing Activities
B80: Capital Expenditure (Capex) | D80: =-(D4*Assumptions!C13) -> -1578.954 | E80: =-(E4*Assumptions!D13) -> -1973.6925 | F80: =-(F4*Assumptions!E13) -> -1973.6925 | G80: =-(G4*Assumptions!F13) -> -2269.7464 | H80: =-(H4*Assumptions!G13) -> -2033.6928
B81: Interest Reeceived | D81: =D5 -> 1184.7 | E81: =E5 -> 1303.17 | F81: =F5 -> 1433.487 | G81: =G5 -> 1576.8357 | H81: =H5 -> 1734.5193
B82: Investment purchases/redemptions | D82: 0 | E82: 0 | F82: 0 | G82: 0 | H82: 0
B83: Net Cash from Investing Activities | D83: =D80+D81+D82 -> -394.254 | E83: =E80+E81+E82 -> -670.5225 | F83: =F80+F81+F82 -> -540.2055 | G83: =G80+G81+G82 -> -692.91067 | H83: =H80+H81+H82 -> -299.17348
B85: Financing Activities
B86: Financing cash flow | D86: =-D10 -> -154 | E86: =-E10 -> -154 | F86: =-F10 -> -154 | G86: =-G10 -> -154 | H86: =-H10 -> -154
B87: Lease Principal Repayment | D87: =Assumptions!C23 -> -80 | E87: =Assumptions!D23 -> -125 | F87: =Assumptions!E23 -> -100 | G87: =Assumptions!F23 -> -121.66667 | H87: =Assumptions!G23 -> -121.66667
B88: Equity issuance | D88: 0 | E88: 0 | F88: 0 | G88: 0 | H88: 0
B89: Net Cash from Financing Activities | D89: =SUM(D86:D88) -> -234 | E89: =SUM(E86:E88) -> -279 | F89: =SUM(F86:F88) -> -254 | G89: =SUM(G86:G88) -> -275.66667 | H89: =SUM(H86:H88) -> -275.66667
B91: Net Change in Cash | D91: =D77+D83+D89 -> 680.1025 | E91: =E77+E83+E89 -> 1323.2121 | F91: =F77+F83+F89 -> 2683.3196 | G91: =G77+G83+G89 -> 3905.3724 | H91: =H77+H83+H89 -> 5425.6995
B92: Opening Cash | D92: ='Historical Data'!E53 -> 666 | E92: =D93 -> 1346.1025 | F92: =E93 -> 2669.3146 | G92: =F93 -> 5352.6342 | H92: =G93 -> 9258.0066
B93: Closing Cash | D93: =D91+D92+0+0 -> 1346.1025 | E93: =E91+E92+0+0 -> 2669.3146 | F93: =F91+F92+0+0 -> 5352.6342 | G93: =G91+G92+0+0 -> 9258.0066 | H93: =H91+H92+0+0 -> 14683.706
B95: BS Check | C95: =C40-C62 -> 0 | D95: =D40-D62 -> 0 | E95: =E40-E62 -> 0 | F95: =F40-F62 -> 0 | G95: =G40-G62 -> 0 | H95: =H40-H62 -> 0

Sheet Operational Drivers and Metric
B2: Historical Margin Analysis:
B3: Metric | C3: FY23 | D3: FY24 | E3: FY25
B4: Revenue Growth % | D4: =('Historical Data'!D15-'Historical Data'!C15)/'Historical Data'!C15 -> 0.71125865 | E4: =('Historical Data'!E15-'Historical Data'!D15)/'Historical Data'!D15 -> 0.67104177
B5: Gross Margin % | C5: 0 | D5: 0 | E5: 0
B6: EBITDA Margin % | C6: =(('Historical Data'!C17-'Historical Data'!C20-'Historical Data'!C21-'Historical Data'!C22-'Historical Data'!C25)/'Historical Data'!C15) -> -0.074586806 | D6: =(('Historical Data'!D17-'Historical Data'!D20-'Historical Data'!D21-'Historical Data'!D22-'Historical Data'!D25)/'Historical Data'!D15) -> 0.073386165 | E6: =(('Historical Data'!E17-'Historical Data'!E20-'Historical Data'!E21-'Historical Data'!E22-'Historical Data'!E25)/'Historical Data'!E15) -> 0.084671244
B7: EBIT Margin % | C7: =C6-('Historical Data'!C24/'Historical Data'!C15) -> -0.13631869 | D7: =D6-('Historical Data'!D24/'Historical Data'!D15) -> 0.029965329 | E7: =E6-('Historical Data'!E24/'Historical Data'!E15) -> 0.042039223
B8: Net Margin % | C8: ='Historical Data'!C29/'Historical Data'!C15 -> -0.14945614 | D8: ='Historical Data'!D29/'Historical Data'!D15 -> 0.02897474 | E8: ='Historical Data'!E29/'Historical Data'!E15 -> 0.026033691
B9: Employee Cost % Revenue | C9: ='Historical Data'!C22/'Historical Data'!C15 -> 0.20695013 | D9: ='Historical Data'!D22/'Historical Data'!D15 -> 0.13694898 | E9: ='Historical Data'!E22/'Historical Data'!E15 -> 0.12636467
B10: Other Expenses % Revenue | C10: ='Historical Data'!C25/'Historical Data'!C15 -> 0.76691623 | D10: ='Historical Data'!D25/'Historical Data'!D15 -> 0.6216774 | E10: ='Historical Data'!E25/'Historical Data'!E15 -> 0.56725782
B11: D&A % Revenue | C11: ='Historical Data'!C24/'Historical Data'!C15 -> 0.061731883 | D11: ='Historical Data'!D24/'Historical Data'!D15 -> 0.043420835 | E11: ='Historical Data'!E24/'Historical Data'!E15 -> 0.042632021
B12: Effective Tax Rate | C12: ='Historical Data'!C28/'Historical Data'!C27 -> -0.043392505 | D12: ='Historical Data'!D28/'Historical Data'!D27 -> -0.20618557 | E12: ='Historical Data'!E28/'Historical Data'!E27 -> 0.24390244
B14: Working Capital Metrics:
B15: Metric | C15: FY23 | D15: FY24 | E15: FY25 | F15: FY26 | G15: FY27
B16: Receivable Days | C16: ='Historical Data'!C52/'Historical Data'!C15*365 -> 23.563356 | D16: ='Historical Data'!D52/'Historical Data'!D15*365 -> 23.92356 | E16: ='Historical Data'!E52/'Historical Data'!E15*365 -> 35.088179
B17: Payable Days | C17: ='Historical Data'!C79/'Historical Data'!C20*365 -> 172.34701 | D17: ='Historical Data'!D79/'Historical Data'!D20*365 -> 112.01593 | E17: ='Historical Data'!E79/'Historical Data'!E20*365 -> 99.175659
B18: Inventory Days | C18: ='Historical Data'!C50/'Historical Data'!C20*365 -> 21.067455 | D18: ='Historical Data'!D50/'Historical Data'!D20*365 -> 11.125736 | E18: ='Historical Data'!E50/'Historical Data'!E20*365 -> 11.363878
B20: Forecast Assumptions:
B21: Assumption | C21: FY26 | D21: FY27 | E21: FY28
B22: Revenue Growth | C22: =Assumptions!C3 -> 0.3 | D22: =Assumptions!D3 -> 0.25 | E22: =Assumptions!E3 -> 0.2
B23: EBITDA Margin | C23: =1-Assumptions!C5-Assumptions!C6-Assumptions!C7 -> 0.045 | D23: =1-Assumptions!D5-Assumptions!D6-Assumptions!D7 -> 0.07 | E23: =1-Assumptions!E5-Assumptions!E6-Assumptions!E7 -> 0.095
B24: Tax Rate | C24: =Assumptions!C10 -> 0.25 | D24: =Assumptions!D10 -> 0.25 | E24: =Assumptions!E10 -> 0.25
B25: Receivable Days | C25: =Assumptions!C11 -> 35 | D25: =Assumptions!D11 -> 34 | E25: =Assumptions!E11 -> 33
B26: Payable Days | C26: =Assumptions!C12 -> 95 | D26: =Assumptions!D12 -> 92 | E26: =Assumptions!E12 -> 90
B27: Capex % Revenue | C27: =Assumptions!C13 -> 0.06 | D27: =Assumptions!D13 -> 0.06 | E27: =Assumptions!E13 -> 0.05

Sheet Valuation Output
B2: OPERATING METRICS | C2: FY26 | D2: FY27 | E2: FY28
B3: Revenue | C3: ='Financial Model'!D4 -> 26315.9 | D3: ='Financial Model'!E4 -> 32894.875 | E3: ='Financial Model'!F4 -> 39473.85
B4: Revenue Growth % | C4: ='Financial Model'!D4/'Financial Model'!C4-1 -> 0.3 | D4: ='Financial Model'!E4/'Financial Model'!D4-1 -> 0.25 | E4: ='Financial Model'!F4/'Financial Model'!E4-1 -> 0.2
B5: EBITDA | C5: ='Financial Model'!D13+'Financial Model'!D10+'Financial Model'!D9 -> 2368.9155 | D5: ='Financial Model'!E13+'Financial Model'!E10+'Financial Model'!E9 -> 3605.8112 | E5: ='Financial Model'!F13+'Financial Model'!F10+'Financial Model'!F9 -> 5183.5028
B6: EBITDA Margin% | C6: =C5/'Financial Model'!D4 -> 0.090018411 | D6: =D5/'Financial Model'!E4 -> 0.1096162 | E6: =E5/'Financial Model'!F4 -> 0.13131485
B7: PAT | C7: ='Financial Model'!D15 -> 871.70963 | D7: ='Financial Model'!E15 -> 1602.0122 | E7: ='Financial Model'!F15 -> 2587.9116
B8: PAT Margin % | C8: =C7/'Financial Model'!D4 -> 0.033124827 | D8: =D7/'Financial Model'!E4 -> 0.048700966 | E8: =E7/'Financial Model'!F4 -> 0.065560151
B10: BALANCE SHEET METRICS | C10: FY26 | D10: FY27 | E10: FY28
B11: Net Working Capital | C11: ='Financial Model'!D28-'Financial Model'!D60 -> 9388.3916 | D11: ='Financial Model'!E28-'Financial Model'!E60 -> 11022.506 | E11: ='Financial Model'!F28-'Financial Model'!F60 -> 13985.679
B12: ROIC(later) | C12: 0 | D12: 0 | E12: 0
B13: Net Cash | C13: =('Financial Model'!D27+'Financial Model'!D24+'Financial Model'!D23)-('Financial Model'!D49+'Financial Model'!D55) -> 4361.1025 | D13: =('Financial Model'!E27+'Financial Model'!E24+'Financial Model'!E23)-('Financial Model'!E49+'Financial Model'!E55) -> 5509.3146 | E13: =('Financial Model'!F27+'Financial Model'!F24+'Financial Model'!F23)-('Financial Model'!F49+'Financial Model'!F55) -> 8042.6342
B15: CASH FLOW METRICS | C15: FY26 | D15: FY27 | E15: FY28
B16: CFO | C16: ='Financial Model'!D77 -> 1308.3565 | D16: ='Financial Model'!E77 -> 2272.7346 | E16: ='Financial Model'!F77 -> 3477.5251
B17: FCF | C17: ='Financial Model'!D77+'Financial Model'!D80 -> -270.5975 | D17: ='Financial Model'!E77+'Financial Model'!E80 -> 299.04208 | E17: ='Financial Model'!F77+'Financial Model'!F80 -> 1503.8326
B19: DCF ASSUMPTION | C19: Value
B20: WACC | C20: 0.11
B21: Terminal Growth Rate | C21: 0.04
B22: Terminal Year | C22: FY30
B23: Shares Outstanding | C23: ='Historical Data'!E63 -> 907
B25: FCFF Schedule | C25: FY25 | D25: FY26 | E25: FY27 | F25: FY28 | G25: FY29 | H25: FY30
B26: EBIT | D26: ='Financial Model'!D13+'Financial Model'!D10 -> 1316.2795 | E26: ='Financial Model'!E13+'Financial Model'!E10 -> 2290.0162 | F26: ='Financial Model'!F13+'Financial Model'!F10 -> 3604.5488 | G26: ='Financial Model'!G13+'Financial Model'!G10 -> 5208.4299 | H26: ='Financial Model'!H13+'Financial Model'!H10 -> 6564.5396
B27: Tax | D27: =D26*Assumptions!C10 -> 329.06988 | E27: =E26*Assumptions!D10 -> 572.50406 | F27: =F26*Assumptions!E10 -> 901.13719 | G27: =G26*Assumptions!F10 -> 1302.1075 | H27: =H26*Assumptions!G10 -> 1641.1349
B28: NOPAT | D28: =D26-D27 -> 987.20963 | E28: =E26-E27 -> 1717.5122 | F28: =F26-F27 -> 2703.4116 | G28: =G26-G27 -> 3906.3224 | H28: =H26-H27 -> 4923.4047
B29: D&A | D29: ='Financial Model'!D9 -> 1052.636 | E29: ='Financial Model'!E9 -> 1315.795 | F29: ='Financial Model'!F9 -> 1578.954 | G29: ='Financial Model'!G9 -> 1815.7971 | H29: ='Financial Model'!H9 -> 2033.6928
B30: Capex | D30: ='Financial Model'!D80 -> -1578.954 | E30: ='Financial Model'!E80 -> -1973.6925 | F30: ='Financial Model'!F80 -> -1973.6925 | G30: ='Financial Model'!G80 -> -2269.7464 | H30: ='Financial Model'!H80 -> -2033.6928
B31: Working Capital | D31: ='Financial Model'!D21+'Financial Model'!D22+'Financial Model'!D26-'Financial Model'!D58-'Financial Model'!D57 -> 1441.2891 | E31: ='Financial Model'!E21+'Financial Model'!E22+'Financial Model'!E26-'Financial Model'!E58-'Financial Model'!E57 -> 1787.1917 | F31: ='Financial Model'!F21+'Financial Model'!F22+'Financial Model'!F26-'Financial Model'!F58-'Financial Model'!F57 -> 2097.0452 | G31: ='Financial Model'!G21+'Financial Model'!G22+'Financial Model'!G26-'Financial Model'!G58-'Financial Model'!G57 -> 2356.8793 | H31: ='Financial Model'!H21+'Financial Model'!H22+'Financial Model'!H26-'Financial Model'!H58-'Financial Model'!H57 -> 2617.4178
B32: Change in working capital | C32: ='Financial Model'!C21+'Financial Model'!C22+'Financial Model'!C26-'Financial Model'!C58-'Financial Model'!C57 -> 1058 | D32: =D31-C32 -> 383.28913 | E32: =E31-D31 -> 345.90261 | F32: =F31-E31 -> 309.85343 | G32: =G31-F31 -> 259.83412 | H32: =H31-G31 -> 260.53847
B33: FCFF | D33: =D28+D29+D30-D32 -> 77.602496 | E33: =E28+E29+E30-E32 -> 713.71208 | F33: =F28+F29+F30-F32 -> 1998.8196 | G33: =G28+G29+G30-G32 -> 3192.539 | H33: =H28+H29+H30-H32 -> 4662.8662
B34: Discount Factor | D34: =1/(1+C20)^1 -> 0.9009009 | E34: =1/(1+C20)^2 -> 0.81162243 | F34: =1/(1+C20)^3 -> 0.73119138 | G34: =1/(1+C20)^4 -> 0.65873097 | H34: =1/(1+C20)^5 -> 0.59345133
B35: PV of FCFF | D35: =D33*D34 -> 69.912159 | E35: =E33*E34 -> 579.26473 | F35: =F33*F34 -> 1461.5197 | G35: =G33*G34 -> 2103.0243 | H35: =H33*H34 -> 2767.1841
B36: Terminal Value | H36: =H33*(1+C21)/(C20-C21) -> 69276.869
B37: PV of Terminal Value | H37: =H36*H34 -> 41112.45
B39: VALUATION SUMMARY | D39: Value
B40: Enterprise Value | D40: =SUM(D35:H35)+H37 -> 48093.355
B41: Cash | D41: ='Financial Model'!H27+'Financial Model'!H23+'Financial Model'!H24 -> 19903.706
B42: Debt | D42: ='Financial Model'!H55+'Financial Model'!H49 -> 2833.3333
B43: Equity Value | D43: =D40+D41-D42 -> 65163.728
B44: Shares Outstanding | D44: =C23 -> 907
B45: Intrinsic Value Per Share | D45: =D43/D44 -> 71.845345
B47: SENSITIVITY ANALYSIS
B48: WACC/g | D48: 0.03 | E48: 0.04 | F48: 0.05
B49: 0.1 | D49: 73.77 | E49: 82.13 | F49: 93.84
B50: 0.11 | D50: 65.8 | E50: 71.85 | F50: 79.91
B51: 0.12 | D51: 59.63 | E51: 64.17 | F51: 70
B53: SCENARIO SUMMARY
B54: Scenario | D54: WACC | E54: Growth | F54: Value per Share
B55: Bear | D55: 0.12 | E55: 0.03 | F55: =D51 -> 59.63
B56: Base | D56: 0.11 | E56: 0.04 | F56: =E50 -> 71.85
B57: Bull | D57: 0.1 | E57: 0.05 | F57: =F49 -> 93.84
B59: REVERSE DCF ANALYSIS
B60: Reverse DCF | D60: Value
B61: Market Price | D61: 264
B62: Base Case DCF | D62: =F56 -> 71.85
B63: Market Premium to Base DCF | D63: =(D61-D62)/D62 -> 2.6743215
B64: Implied Terminal Growth @ 11% WACC | D64: 0.0959
B65: Implied WACC @ 4% Terminal Growth | D65: 0.0572
